spvm/__init__.py
spvm/cmd.py
spvm/config.py
spvm/core.py
spvm/ioutils.py
spvm/metautils.py
spvm/res/pyp.json
spvm/res/setup.py
spvm-0.0.39.dist-info/METADATA
spvm-0.0.39.dist-info/RECORD
spvm-0.0.39.dist-info/WHEEL
spvm-0.0.39.dist-info/entry_points.txt
spvm-0.0.39.dist-info/top_level.txt
