Metadata-Version: 2.1
Name: spvm
Version: 0.0.39
Summary: Simple Python Versioning Manager
Home-page: https://github.com/win32gg/spvm
Author: win32gg
Author-email: gregor.jouet@laposte.net
License: MIT
Platform: UNKNOWN
Requires-Python: >=3.4, <4
Requires-Dist: Click
Requires-Dist: colorama
Requires-Dist: pyflakes
Requires-Dist: pycodestyle
Requires-Dist: autopep8
Requires-Dist: pytest
Requires-Dist: twine
Requires-Dist: splogger
Requires-Dist: docker-py
Requires-Dist: wrapt
Requires-Dist: python-gnupg
